[
  {
    "objectId": 1,
    "objectId1": 1,
    "ags": "48",
    "name": "Bjelovarsko-bilogorska",
    "type": "Zupanija",
    "state": "Bjelovarsko-bilogorska",
    "population": 0,
    "cases": 288,
    "deaths": 2,
    "deathRate": 0.0,
    "lastDayCases": [
      8
    ],
    "lastUpdate": "2020-10-06 08:41:00"
  },
  {
    "objectId": 2,
    "objectId1": 2,
    "ags": "22",
    "name": "Brodsko-posavska",
    "type": "Zupanija",
    "state": "Brodsko-posavska",
    "population": 0,
    "cases": 653,
    "deaths": 6,
    "deathRate": 0.0,
    "lastDayCases": [
      3
    ],
    "lastUpdate": "2020-10-06 08:41:00"
  },
  {
    "objectId": 3,
    "objectId1": 3,
    "ags": "67",
    "name": "Dubrovačko-neretvanska",
    "type": "Zupanija",
    "state": "Dubrovačko-neretvanska",
    "population": 0,
    "cases": 730,
    "deaths": 15,
    "deathRate": 0.0,
    "lastDayCases": [
      24
    ],
    "lastUpdate": "2020-10-06 08:41:00"
  },
  {
    "objectId": 4,
    "objectId1": 4,
    "ags": "355",
    "name": "Grad Zagreb",
    "type": "Zupanija",
    "state": "Grad Zagreb",
    "population": 0,
    "cases": 3830,
    "deaths": 63,
    "deathRate": 0.0,
    "lastDayCases": [
      60
    ],
    "lastUpdate": "2020-10-06 08:41:00"
  },
  {
    "objectId": 5,
    "objectId1": 5,
    "ags": "10",
    "name": "Istarska",
    "type": "Zupanija",
    "state": "Istarska",
    "population": 0,
    "cases": 484,
    "deaths": 12,
    "deathRate": 0.0,
    "lastDayCases": [
      0
    ],
    "lastUpdate": "2020-10-06 08:41:00"
  },
  {
    "objectId": 6,
    "objectId1": 6,
    "ags": "27",
    "name": "Karlovačka",
    "type": "Zupanija",
    "state": "Karlovačka",
    "population": 0,
    "cases": 386,
    "deaths": 3,
    "deathRate": 0.0,
    "lastDayCases": [
      0
    ],
    "lastUpdate": "2020-10-06 08:41:00"
  },
  {
    "objectId": 7,
    "objectId1": 7,
    "ags": "26",
    "name": "Koprivničko-križevačka",
    "type": "Zupanija",
    "state": "Koprivničko-križevačka",
    "population": 0,
    "cases": 249,
    "deaths": 16,
    "deathRate": 0.0,
    "lastDayCases": [
      3
    ],
    "lastUpdate": "2020-10-06 08:41:00"
  },
  {
    "objectId": 8,
    "objectId1": 8,
    "ags": "98",
    "name": "Krapinsko-zagorska županija",
    "type": "Zupanija",
    "state": "Krapinsko-zagorska županija",
    "population": 0,
    "cases": 471,
    "deaths": 2,
    "deathRate": 0.0,
    "lastDayCases": [
      15
    ],
    "lastUpdate": "2020-10-06 08:41:00"
  },
  {
    "objectId": 9,
    "objectId1": 9,
    "ags": "60",
    "name": "Ličko-senjska",
    "type": "Zupanija",
    "state": "Ličko-senjska",
    "population": 0,
    "cases": 235,
    "deaths": 1,
    "deathRate": 0.0,
    "lastDayCases": [
      23
    ],
    "lastUpdate": "2020-10-06 08:41:00"
  },
  {
    "objectId": 10,
    "objectId1": 10,
    "ags": "63",
    "name": "Međimurska",
    "type": "Zupanija",
    "state": "Međimurska",
    "population": 0,
    "cases": 218,
    "deaths": 0,
    "deathRate": 0.0,
    "lastDayCases": [
      12
    ],
    "lastUpdate": "2020-10-06 08:41:00"
  },
  {
    "objectId": 11,
    "objectId1": 11,
    "ags": "62",
    "name": "Osječko-baranjska",
    "type": "Zupanija",
    "state": "Osječko-baranjska",
    "population": 0,
    "cases": 1086,
    "deaths": 41,
    "deathRate": 0.0,
    "lastDayCases": [
      12
    ],
    "lastUpdate": "2020-10-06 08:41:00"
  },
  {
    "objectId": 12,
    "objectId1": 12,
    "ags": "39",
    "name": "Požeško-slavonska",
    "type": "Zupanija",
    "state": "Požeško-slavonska",
    "population": 0,
    "cases": 451,
    "deaths": 2,
    "deathRate": 0.0,
    "lastDayCases": [
      5
    ],
    "lastUpdate": "2020-10-06 08:41:00"
  },
  {
    "objectId": 13,
    "objectId1": 13,
    "ags": "88",
    "name": "Primorsko-goranska",
    "type": "Zupanija",
    "state": "Primorsko-goranska",
    "population": 0,
    "cases": 748,
    "deaths": 16,
    "deathRate": 0.0,
    "lastDayCases": [
      5
    ],
    "lastUpdate": "2020-10-06 08:41:00"
  },
  {
    "objectId": 14,
    "objectId1": 14,
    "ags": "18",
    "name": "Šibensko-kninska",
    "type": "Zupanija",
    "state": "Šibensko-kninska",
    "population": 0,
    "cases": 574,
    "deaths": 6,
    "deathRate": 0.0,
    "lastDayCases": [
      4
    ],
    "lastUpdate": "2020-10-06 08:41:00"
  },
  {
    "objectId": 15,
    "objectId1": 15,
    "ags": "105",
    "name": "Sisačko-moslavačka",
    "type": "Zupanija",
    "state": "Sisačko-moslavačka",
    "population": 0,
    "cases": 388,
    "deaths": 4,
    "deathRate": 0.0,
    "lastDayCases": [
      7
    ],
    "lastUpdate": "2020-10-06 08:41:00"
  },
  {
    "objectId": 16,
    "objectId1": 16,
    "ags": "184",
    "name": "Splitsko-dalmatinska",
    "type": "Zupanija",
    "state": "Splitsko-dalmatinska",
    "population": 0,
    "cases": 4153,
    "deaths": 78,
    "deathRate": 0.0,
    "lastDayCases": [
      52
    ],
    "lastUpdate": "2020-10-06 08:41:00"
  },
  {
    "objectId": 17,
    "objectId1": 17,
    "ags": "18",
    "name": "Varaždinska",
    "type": "Zupanija",
    "state": "Varaždinska",
    "population": 0,
    "cases": 243,
    "deaths": 3,
    "deathRate": 0.0,
    "lastDayCases": [
      1
    ],
    "lastUpdate": "2020-10-06 08:41:00"
  },
  {
    "objectId": 18,
    "objectId1": 18,
    "ags": "32",
    "name": "Virovitičko-podravska",
    "type": "Zupanija",
    "state": "Virovitičko-podravska",
    "population": 0,
    "cases": 260,
    "deaths": 4,
    "deathRate": 0.0,
    "lastDayCases": [
      5
    ],
    "lastUpdate": "2020-10-06 08:41:00"
  },
  {
    "objectId": 19,
    "objectId1": 19,
    "ags": "107",
    "name": "Vukovarsko-srijemska",
    "type": "Zupanija",
    "state": "Vukovarsko-srijemska",
    "population": 0,
    "cases": 959,
    "deaths": 11,
    "deathRate": 0.0,
    "lastDayCases": [
      16
    ],
    "lastUpdate": "2020-10-06 08:41:00"
  },
  {
    "objectId": 20,
    "objectId1": 20,
    "ags": "27",
    "name": "Zadarska",
    "type": "Zupanija",
    "state": "Zadarska",
    "population": 0,
    "cases": 775,
    "deaths": 9,
    "deathRate": 0.0,
    "lastDayCases": [
      10
    ],
    "lastUpdate": "2020-10-06 08:41:00"
  },
  {
    "objectId": 21,
    "objectId1": 21,
    "ags": "117",
    "name": "Zagrebačka ",
    "type": "Zupanija",
    "state": "Zagrebačka ",
    "population": 0,
    "cases": 903,
    "deaths": 10,
    "deathRate": 0.0,
    "lastDayCases": [
      22
    ],
    "lastUpdate": "2020-10-06 08:41:00"
  }
]